tgz/__init__.py
tgz/tgz.py
telegramz-0.0.0.0.1.dist-info/WHEEL
telegramz-0.0.0.0.1.dist-info/METADATA
telegramz-0.0.0.0.1.dist-info/RECORD
